cernrequests/__init__.py
cernrequests/cern-cacert.pem
cernrequests/certs.py
cernrequests/cookies.py
cernrequests/core.py
cernrequests/token.py
cernrequests-0.5.0.dist-info/LICENSE
cernrequests-0.5.0.dist-info/METADATA
cernrequests-0.5.0.dist-info/WHEEL
cernrequests-0.5.0.dist-info/top_level.txt
cernrequests-0.5.0.dist-info/RECORD
