Metadata-Version: 2.1
Name: cernrequests
Version: 0.5.0
Home-page: https://github.com/CMSTrackerDPG/cernrequests
Author: Peter Stein
Author-email: peter.stein@cern.ch
Maintainer: CMS DQM team
Maintainer-email: cms-dqm-coreTeam@cern.ch
Classifier: License :: OSI Approved :: GNU General Public License v3 (GPLv3)
License-File: LICENSE
Requires-Dist: requests
Requires-Dist: future
Requires-Dist: python-dotenv
Requires-Dist: pyjwt
